setup.py
funniest/__init__.py
ouss_funniest.egg-info/PKG-INFO
ouss_funniest.egg-info/SOURCES.txt
ouss_funniest.egg-info/dependency_links.txt
ouss_funniest.egg-info/not-zip-safe
ouss_funniest.egg-info/top_level.txt